rinoh_typeface_texgyrebonum/GUST-FONT-LICENSE.txt
rinoh_typeface_texgyrebonum/README-TeX-Gyre-Bonum.txt
rinoh_typeface_texgyrebonum/__init__.py
rinoh_typeface_texgyrebonum/texgyrebonum-bold.otf
rinoh_typeface_texgyrebonum/texgyrebonum-bolditalic.otf
rinoh_typeface_texgyrebonum/texgyrebonum-italic.otf
rinoh_typeface_texgyrebonum/texgyrebonum-regular.otf
rinoh_typeface_texgyrebonum-0.1.1.dist-info/DESCRIPTION.rst
rinoh_typeface_texgyrebonum-0.1.1.dist-info/METADATA
rinoh_typeface_texgyrebonum-0.1.1.dist-info/RECORD
rinoh_typeface_texgyrebonum-0.1.1.dist-info/WHEEL
rinoh_typeface_texgyrebonum-0.1.1.dist-info/entry_points.txt
rinoh_typeface_texgyrebonum-0.1.1.dist-info/metadata.json
rinoh_typeface_texgyrebonum-0.1.1.dist-info/top_level.txt
