Metadata-Version: 2.0
Name: rinoh-typeface-texgyrebonum
Version: 0.1.1
Summary: TeX Gyre Bonum typeface
Home-page: https://github.com/brechtm/rinoh-typeface-texgyrebonum
Author: Brecht Machiels
Author-email: brecht@mos6581.org
License: GUST Font License (GFL)
Keywords: opentype font
Platform: UNKNOWN
Classifier: Intended Audience :: Developers
Classifier: Intended Audience :: End Users/Desktop
Classifier: Operating System :: OS Independent
Classifier: Programming Language :: Python
Classifier: Programming Language :: Python :: 3
Classifier: Topic :: Text Processing :: Fonts
Requires-Dist: rinohtype
